streamlit_cld_upload_widget/__init__.py
streamlit_cld_upload_widget/frontend/index.html
streamlit_cld_upload_widget/frontend/main.js
streamlit_cld_upload_widget/frontend/streamlit-component-lib.js
streamlit_cld_upload_widget/frontend/style.css
streamlit_cld_upload_widget-0.1.0.dist-info/LICENSE
streamlit_cld_upload_widget-0.1.0.dist-info/METADATA
streamlit_cld_upload_widget-0.1.0.dist-info/WHEEL
streamlit_cld_upload_widget-0.1.0.dist-info/top_level.txt
streamlit_cld_upload_widget-0.1.0.dist-info/RECORD
