Metadata-Version: 2.1
Name: streamlit-cld-upload-widget
Version: 0.1.0
Summary: Streamlit component that allows you to embed Cloudinary's Uploader Widget
Author: Akshay Ranganath
Author-email: akshay.ranganath@cloudinary.com
Requires-Python: >=3.7
License-File: LICENSE
Requires-Dist: streamlit (>=1.2)
Requires-Dist: jinja2
